building_controller_forecast/DataPreprocessing.py
building_controller_forecast/DynamicImporter.py
building_controller_forecast/Forecasting.py
building_controller_forecast/GetPredictionIntervals.py
building_controller_forecast/StoreRetrieveModel.py
building_controller_forecast/StoreRetrieveModelAws.py
building_controller_forecast/StoreRetrieveModelPython.py
building_controller_forecast/__init__.py
building_controller_forecast-0.1.0.dist-info/METADATA
building_controller_forecast-0.1.0.dist-info/WHEEL
building_controller_forecast-0.1.0.dist-info/top_level.txt
building_controller_forecast-0.1.0.dist-info/RECORD
