Metadata-Version: 2.1
Name: building-controller-forecast
Version: 0.1.0
Summary: Building controller forecasting lib
Home-page: UNKNOWN
Author: Prajakta Gujarathi
Author-email: UNKNOWN
License: BuildingsIOT
Platform: UNKNOWN
Requires-Dist: aws-lambda-context (==1.1.0)
Requires-Dist: boto3 (~=1.11.16)
Requires-Dist: flask (==1.1.2)
Requires-Dist: hszinc (==1.2.3)
Requires-Dist: joblib (==0.13.2)
Requires-Dist: numpy (==1.17.4)
Requires-Dist: pandas (~=0.25)
Requires-Dist: scikit-learn (==0.22)
Requires-Dist: scipy (==1.3.1)
Requires-Dist: simplejson (==3.17.0)
Requires-Dist: sklearn (==0.0)
Requires-Dist: xgboost (==0.82)
Requires-Dist: statsmodels (==0.10.0rc2)
Requires-Dist: gunicorn (==20.0.4)
Requires-Dist: wheel (==0.33.6)
Requires-Dist: requests (==2.18.4)
Requires-Dist: flask-oidc (~=1.4.0)
Requires-Dist: redis (~=3.5.3)
Requires-Dist: rq (~=1.8.0)
Requires-Dist: Flask-RQ2 (~=18.3)
Requires-Dist: moto (~=1.3.14)
Requires-Dist: mock (~=2.0.0)
Requires-Dist: pytest (~=5.4.1)
Requires-Dist: botocore (~=1.14.16)
Requires-Dist: pytest-cov (~=2.9.0)
